Metadata-Version: 2.1
Name: skeletal-animation
Version: 1.1.2.1
Summary: Standalone package for skeletal animation
Home-page: https://gitlab-etu.ing.he-arc.ch/isc/general/python-skeletal-animation/tb-animation-squelettale-fork
Author: Dimitri "Kerzoum" Kohler
Author-email: dimitri.kohler@he-arc.ch
Maintainer: Christophe "chrismeunier" Muller
Maintainer-email: christophe.muller@he-arc.ch
License: MIT
Classifier: Development Status :: 3 - Alpha
Classifier: Intended Audience :: Developers
Classifier: Topic :: Software Development
Classifier: License :: OSI Approved :: MIT License
Classifier: Programming Language :: Python :: 3.10
License-File: LICENSE.txt
Requires-Dist: setuptools
Requires-Dist: wheel
Requires-Dist: numpy-quaternion >=2022.0.0
Requires-Dist: numpy
Requires-Dist: pygltflib >=1.15.0
Requires-Dist: bpy >=3.4.0
